client/__init__.py
client/add_contact.py
client/client_db.py
client/del_contact.py
client/main_window.py
client/start_dialog.py
client/transport.py
common/Descriptor.py
common/Metaclass.py
common/__init__.py
common/decos.py
common/errors.py
common/logs_decorator.py
common/utils.py
common/variables.py
log_config/__init__.py
log_config/client_log_config.py
log_config/console_log_config.py
log_config/server_log_config.py
unit_tests/__init__.py
unit_tests/test_client.py
unit_tests/test_server.py
unit_tests/test_utils.py
client_asyn_chat-0.2.dist-info/METADATA
client_asyn_chat-0.2.dist-info/WHEEL
client_asyn_chat-0.2.dist-info/top_level.txt
client_asyn_chat-0.2.dist-info/RECORD
