Metadata-Version: 2.1
Name: client-asyn-chat
Version: 0.2
Summary: Client packet
Author: Alex Ya
Author-email: ya_alexander@mail.ru
